{
  "building": "诚园-甲",
  "campus": "苏州校区",
  "total_rooms": 144,
  "rooms": {
    "诚园-甲-425": {
      "current_balance": 175.13,
      "last_updated": "20260707"
    },
    "诚园-甲-210": {
      "current_balance": 333.57,
      "last_updated": "20260707"
    },
    "诚园-甲-211": {
      "current_balance": 265.95,
      "last_updated": "20260707"
    },
    "诚园-甲-305": {
      "current_balance": 85.75,
      "last_updated": "20260707"
    },
    "诚园-甲-223": {
      "current_balance": 182.52,
      "last_updated": "20260707"
    },
    "诚园-甲-503": {
      "current_balance": 162.95,
      "last_updated": "20260707"
    },
    "诚园-甲-407": {
      "current_balance": 117.31,
      "last_updated": "20260707"
    },
    "诚园-甲-618": {
      "current_balance": 9.1,
      "last_updated": "20260707"
    },
    "诚园-甲-409": {
      "current_balance": 141.15,
      "last_updated": "20260707"
    },
    "诚园-甲-404": {
      "current_balance": 59.12,
      "last_updated": "20260707"
    },
    "诚园-甲-225": {
      "current_balance": 117.34,
      "last_updated": "20260707"
    },
    "诚园-甲-427": {
      "current_balance": 116.47,
      "last_updated": "20260707"
    },
    "诚园-甲-414": {
      "current_balance": 490.71,
      "last_updated": "20260707"
    },
    "诚园-甲-522": {
      "current_balance": 318.81,
      "last_updated": "20260707"
    },
    "诚园-甲-626": {
      "current_balance": 259.12,
      "last_updated": "20260707"
    },
    "诚园-甲-708": {
      "current_balance": 196.32,
      "last_updated": "20260707"
    },
    "诚园-甲-325": {
      "current_balance": 37.15,
      "last_updated": "20260707"
    },
    "诚园-甲-703": {
      "current_balance": 10.6,
      "last_updated": "20260707"
    },
    "诚园-甲-620": {
      "current_balance": 33.04,
      "last_updated": "20260707"
    },
    "诚园-甲-205": {
      "current_balance": 42.35,
      "last_updated": "20260707"
    },
    "诚园-甲-410": {
      "current_balance": 91.64,
      "last_updated": "20260707"
    },
    "诚园-甲-319": {
      "current_balance": 5.63,
      "last_updated": "20260707"
    },
    "诚园-甲-526": {
      "current_balance": 720.69,
      "last_updated": "20260707"
    },
    "诚园-甲-406": {
      "current_balance": 56.75,
      "last_updated": "20260707"
    },
    "诚园-甲-605": {
      "current_balance": 185.14,
      "last_updated": "20260707"
    },
    "诚园-甲-408": {
      "current_balance": 14.64,
      "last_updated": "20260707"
    },
    "诚园-甲-521": {
      "current_balance": 11.53,
      "last_updated": "20260707"
    },
    "诚园-甲-502": {
      "current_balance": 403.72,
      "last_updated": "20260707"
    },
    "诚园-甲-303": {
      "current_balance": 335.8,
      "last_updated": "20260707"
    },
    "诚园-甲-617": {
      "current_balance": 66.54,
      "last_updated": "20260707"
    },
    "诚园-甲-506": {
      "current_balance": 198.0,
      "last_updated": "20260707"
    },
    "诚园-甲-619": {
      "current_balance": 253.29,
      "last_updated": "20260617"
    },
    "诚园-甲-423": {
      "current_balance": 96.04,
      "last_updated": "20260707"
    },
    "诚园-甲-227": {
      "current_balance": 157.73,
      "last_updated": "20260707"
    },
    "诚园-甲-422": {
      "current_balance": 125.94,
      "last_updated": "20260707"
    },
    "诚园-甲-307": {
      "current_balance": 98.32,
      "last_updated": "20260707"
    },
    "诚园-甲-704": {
      "current_balance": 125.07,
      "last_updated": "20260707"
    },
    "诚园-甲-613": {
      "current_balance": 173.35,
      "last_updated": "20260707"
    },
    "诚园-甲-520": {
      "current_balance": 105.0,
      "last_updated": "20260707"
    },
    "诚园-甲-525": {
      "current_balance": 91.18,
      "last_updated": "20260707"
    },
    "诚园-甲-508": {
      "current_balance": 421.26,
      "last_updated": "20260707"
    },
    "诚园-甲-513": {
      "current_balance": 266.4,
      "last_updated": "20260707"
    },
    "诚园-甲-201": {
      "current_balance": 71.71,
      "last_updated": "20260707"
    },
    "诚园-甲-203": {
      "current_balance": 13.62,
      "last_updated": "20260707"
    },
    "诚园-甲-323": {
      "current_balance": 240.4,
      "last_updated": "20260707"
    },
    "诚园-甲-706": {
      "current_balance": 85.3,
      "last_updated": "20260707"
    },
    "诚园-甲-519": {
      "current_balance": 198.62,
      "last_updated": "20260707"
    },
    "诚园-甲-222": {
      "current_balance": 207.79,
      "last_updated": "20260707"
    },
    "诚园-甲-206": {
      "current_balance": 101.39,
      "last_updated": "20260707"
    },
    "诚园-甲-113": {
      "current_balance": 147.65,
      "last_updated": "20260707"
    },
    "诚园-甲-416": {
      "current_balance": 163.29,
      "last_updated": "20260707"
    },
    "诚园-甲-420": {
      "current_balance": 440.84,
      "last_updated": "20260707"
    },
    "诚园-甲-302": {
      "current_balance": 191.9,
      "last_updated": "20260707"
    },
    "诚园-甲-317": {
      "current_balance": 243.0,
      "last_updated": "20260707"
    },
    "诚园-甲-504": {
      "current_balance": 340.37,
      "last_updated": "20260707"
    },
    "诚园-甲-413": {
      "current_balance": 589.8,
      "last_updated": "20260707"
    },
    "诚园-甲-511": {
      "current_balance": 42.7,
      "last_updated": "20260707"
    },
    "诚园-甲-505": {
      "current_balance": 62.56,
      "last_updated": "20260707"
    },
    "诚园-甲-315": {
      "current_balance": 537.02,
      "last_updated": "20260707"
    },
    "诚园-甲-403": {
      "current_balance": 57.85,
      "last_updated": "20260707"
    },
    "诚园-甲-421": {
      "current_balance": 0.0,
      "last_updated": "20260707"
    },
    "诚园-甲-212": {
      "current_balance": 326.3,
      "last_updated": "20260707"
    },
    "诚园-甲-313": {
      "current_balance": 53.6,
      "last_updated": "20260707"
    },
    "诚园-甲-702": {
      "current_balance": 204.26,
      "last_updated": "20260707"
    },
    "诚园-甲-524": {
      "current_balance": 183.95,
      "last_updated": "20260707"
    },
    "诚园-甲-509": {
      "current_balance": 174.71,
      "last_updated": "20260707"
    },
    "诚园-甲-515": {
      "current_balance": 228.38,
      "last_updated": "20260707"
    },
    "诚园-甲-318": {
      "current_balance": 329.77,
      "last_updated": "20260707"
    },
    "诚园-甲-207": {
      "current_balance": 249.88,
      "last_updated": "20260707"
    },
    "诚园-甲-415": {
      "current_balance": 118.9,
      "last_updated": "20260707"
    },
    "诚园-甲-217": {
      "current_balance": 236.59,
      "last_updated": "20260707"
    },
    "诚园-甲-709": {
      "current_balance": 23.04,
      "last_updated": "20260707"
    },
    "诚园-甲-623": {
      "current_balance": 38.28,
      "last_updated": "20260707"
    },
    "诚园-甲-314": {
      "current_balance": 82.42,
      "last_updated": "20260707"
    },
    "诚园-甲-606": {
      "current_balance": 154.85,
      "last_updated": "20260707"
    },
    "诚园-甲-609": {
      "current_balance": 539.26,
      "last_updated": "20260707"
    },
    "诚园-甲-412": {
      "current_balance": 256.21,
      "last_updated": "20260707"
    },
    "诚园-甲-202": {
      "current_balance": 24.67,
      "last_updated": "20260707"
    },
    "诚园-甲-308": {
      "current_balance": 0.86,
      "last_updated": "20260707"
    },
    "诚园-甲-711": {
      "current_balance": 156.22,
      "last_updated": "20260707"
    },
    "诚园-甲-204": {
      "current_balance": 313.55,
      "last_updated": "20260707"
    },
    "诚园-甲-221": {
      "current_balance": 5.53,
      "last_updated": "20260707"
    },
    "诚园-甲-324": {
      "current_balance": 98.88,
      "last_updated": "20260707"
    },
    "诚园-甲-224": {
      "current_balance": 239.53,
      "last_updated": "20260707"
    },
    "诚园-甲-310": {
      "current_balance": 96.87,
      "last_updated": "20260707"
    },
    "诚园-甲-516": {
      "current_balance": 19.8,
      "last_updated": "20260707"
    },
    "诚园-甲-218": {
      "current_balance": 34.58,
      "last_updated": "20260707"
    },
    "诚园-甲-405": {
      "current_balance": 0.0,
      "last_updated": "20260707"
    },
    "诚园-甲-411": {
      "current_balance": 791.52,
      "last_updated": "20260707"
    },
    "诚园-甲-710": {
      "current_balance": 55.13,
      "last_updated": "20260707"
    },
    "诚园-甲-622": {
      "current_balance": 102.43,
      "last_updated": "20260707"
    },
    "诚园-甲-316": {
      "current_balance": 63.63,
      "last_updated": "20260707"
    },
    "诚园-甲-701": {
      "current_balance": 136.73,
      "last_updated": "20260707"
    },
    "诚园-甲-607": {
      "current_balance": 219.02,
      "last_updated": "20260707"
    },
    "诚园-甲-517": {
      "current_balance": 131.34,
      "last_updated": "20260707"
    },
    "诚园-甲-510": {
      "current_balance": 235.75,
      "last_updated": "20260707"
    },
    "诚园-甲-309": {
      "current_balance": 297.01,
      "last_updated": "20260707"
    },
    "诚园-甲-615": {
      "current_balance": 165.05,
      "last_updated": "20260707"
    },
    "诚园-甲-311": {
      "current_balance": 96.36,
      "last_updated": "20260707"
    },
    "诚园-甲-624": {
      "current_balance": 196.42,
      "last_updated": "20260707"
    },
    "诚园-甲-424": {
      "current_balance": 130.27,
      "last_updated": "20260707"
    },
    "诚园-甲-326": {
      "current_balance": 1203.05,
      "last_updated": "20260707"
    },
    "诚园-甲-625": {
      "current_balance": 128.85,
      "last_updated": "20260707"
    },
    "诚园-甲-527": {
      "current_balance": 135.25,
      "last_updated": "20260707"
    },
    "诚园-甲-418": {
      "current_balance": 110.93,
      "last_updated": "20260707"
    },
    "诚园-甲-320": {
      "current_balance": 255.85,
      "last_updated": "20260707"
    },
    "诚园-甲-616": {
      "current_balance": 1.28,
      "last_updated": "20260707"
    },
    "诚园-甲-215": {
      "current_balance": 18.11,
      "last_updated": "20260707"
    },
    "诚园-甲-306": {
      "current_balance": 180.77,
      "last_updated": "20260707"
    },
    "诚园-甲-301": {
      "current_balance": 66.79,
      "last_updated": "20260707"
    },
    "诚园-甲-209": {
      "current_balance": 36.24,
      "last_updated": "20260707"
    },
    "诚园-甲-322": {
      "current_balance": 304.15,
      "last_updated": "20260707"
    },
    "诚园-甲-518": {
      "current_balance": 186.41,
      "last_updated": "20260707"
    },
    "诚园-甲-611": {
      "current_balance": 23.59,
      "last_updated": "20260707"
    },
    "诚园-甲-604": {
      "current_balance": 85.76,
      "last_updated": "20260707"
    },
    "诚园-甲-501": {
      "current_balance": 26.25,
      "last_updated": "20260707"
    },
    "诚园-甲-512": {
      "current_balance": 61.33,
      "last_updated": "20260707"
    },
    "诚园-甲-805": {
      "current_balance": 11.17,
      "last_updated": "20260707"
    },
    "诚园-甲-419": {
      "current_balance": 303.51,
      "last_updated": "20260707"
    },
    "诚园-甲-216": {
      "current_balance": 107.05,
      "last_updated": "20260707"
    },
    "诚园-甲-312": {
      "current_balance": 164.95,
      "last_updated": "20260707"
    },
    "诚园-甲-327": {
      "current_balance": 247.45,
      "last_updated": "20260707"
    },
    "诚园-甲-514": {
      "current_balance": 359.61,
      "last_updated": "20260707"
    },
    "诚园-甲-213": {
      "current_balance": 42.8,
      "last_updated": "20260707"
    },
    "诚园-甲-523": {
      "current_balance": 135.47,
      "last_updated": "20260707"
    },
    "诚园-甲-219": {
      "current_balance": 442.86,
      "last_updated": "20260707"
    },
    "诚园-甲-614": {
      "current_balance": 270.18,
      "last_updated": "20260707"
    },
    "诚园-甲-608": {
      "current_balance": 143.53,
      "last_updated": "20260707"
    },
    "诚园-甲-507": {
      "current_balance": 77.45,
      "last_updated": "20260707"
    },
    "诚园-甲-601": {
      "current_balance": 268.43,
      "last_updated": "20260707"
    },
    "诚园-甲-627": {
      "current_balance": 108.95,
      "last_updated": "20260707"
    },
    "诚园-甲-603": {
      "current_balance": 40.41,
      "last_updated": "20260707"
    },
    "诚园-甲-208": {
      "current_balance": 44.1,
      "last_updated": "20260707"
    },
    "诚园-甲-226": {
      "current_balance": 10.08,
      "last_updated": "20260707"
    },
    "诚园-甲-401": {
      "current_balance": 100.95,
      "last_updated": "20260707"
    },
    "诚园-甲-705": {
      "current_balance": 149.43,
      "last_updated": "20260707"
    },
    "诚园-甲-220": {
      "current_balance": 79.24,
      "last_updated": "20260707"
    },
    "诚园-甲-426": {
      "current_balance": 334.2,
      "last_updated": "20260707"
    },
    "诚园-甲-612": {
      "current_balance": 20.2,
      "last_updated": "20260707"
    },
    "诚园-甲-602": {
      "current_balance": 202.88,
      "last_updated": "20260707"
    },
    "诚园-甲-402": {
      "current_balance": 23.07,
      "last_updated": "20260707"
    },
    "诚园-甲-321": {
      "current_balance": 55.21,
      "last_updated": "20260707"
    },
    "诚园-甲-214": {
      "current_balance": 143.19,
      "last_updated": "20260707"
    },
    "诚园-甲-707": {
      "current_balance": 23.96,
      "last_updated": "20260707"
    }
  }
}