{
  "building": "陶园二栋",
  "campus": "鼓楼校区",
  "total_rooms": 337,
  "rooms": {
    "520": {
      "current_balance": 1485.19,
      "last_updated": "20260606"
    },
    "0415": {
      "current_balance": 222.59,
      "last_updated": "20260606"
    },
    "224": {
      "current_balance": 778.58,
      "last_updated": "20260606"
    },
    "808": {
      "current_balance": 565.72,
      "last_updated": "20260606"
    },
    "309": {
      "current_balance": 1967.71,
      "last_updated": "20260606"
    },
    "817": {
      "current_balance": 1811.48,
      "last_updated": "20260606"
    },
    "113": {
      "current_balance": 15.0,
      "last_updated": "20260606"
    },
    "702": {
      "current_balance": 1589.89,
      "last_updated": "20260606"
    },
    "106": {
      "current_balance": 316.97,
      "last_updated": "20260606"
    },
    "415": {
      "current_balance": 222.59,
      "last_updated": "20260606"
    },
    "221": {
      "current_balance": 1007.12,
      "last_updated": "20260606"
    },
    "0601": {
      "current_balance": 954.17,
      "last_updated": "20260606"
    },
    "1016": {
      "current_balance": 846.15,
      "last_updated": "20260606"
    },
    "1108": {
      "current_balance": 1374.13,
      "last_updated": "20260606"
    },
    "413": {
      "current_balance": 1636.78,
      "last_updated": "20260606"
    },
    "707": {
      "current_balance": 2010.09,
      "last_updated": "20260606"
    },
    "1219": {
      "current_balance": 594.24,
      "last_updated": "20260606"
    },
    "1106": {
      "current_balance": 838.71,
      "last_updated": "20260606"
    },
    "1212": {
      "current_balance": 1131.66,
      "last_updated": "20260606"
    },
    "1122": {
      "current_balance": 692.75,
      "last_updated": "20260606"
    },
    "1019": {
      "current_balance": 1934.36,
      "last_updated": "20260606"
    },
    "905": {
      "current_balance": 975.14,
      "last_updated": "20260606"
    },
    "809": {
      "current_balance": 969.74,
      "last_updated": "20260606"
    },
    "606": {
      "current_balance": 1955.31,
      "last_updated": "20260606"
    },
    "601": {
      "current_balance": 954.17,
      "last_updated": "20260606"
    },
    "909": {
      "current_balance": 1741.87,
      "last_updated": "20260606"
    },
    "710": {
      "current_balance": 1024.41,
      "last_updated": "20260606"
    },
    "724": {
      "current_balance": 1055.61,
      "last_updated": "20260606"
    },
    "719": {
      "current_balance": 337.63,
      "last_updated": "20260606"
    },
    "204": {
      "current_balance": 1465.47,
      "last_updated": "20260606"
    },
    "619": {
      "current_balance": 938.95,
      "last_updated": "20260606"
    },
    "0208": {
      "current_balance": 988.2,
      "last_updated": "20260606"
    },
    "0912": {
      "current_balance": 2385.0,
      "last_updated": "20260606"
    },
    "107": {
      "current_balance": 1323.13,
      "last_updated": "20260606"
    },
    "513": {
      "current_balance": 1480.18,
      "last_updated": "20260606"
    },
    "518": {
      "current_balance": 980.34,
      "last_updated": "20260606"
    },
    "1201": {
      "current_balance": 572.01,
      "last_updated": "20260606"
    },
    "504": {
      "current_balance": 1070.37,
      "last_updated": "20260606"
    },
    "321": {
      "current_balance": 770.62,
      "last_updated": "20260606"
    },
    "1208": {
      "current_balance": 993.84,
      "last_updated": "20260606"
    },
    "0212": {
      "current_balance": 2130.77,
      "last_updated": "20260606"
    },
    "102": {
      "current_balance": 1012.44,
      "last_updated": "20260606"
    },
    "215": {
      "current_balance": 1005.3,
      "last_updated": "20260606"
    },
    "1024": {
      "current_balance": 1322.11,
      "last_updated": "20260606"
    },
    "408": {
      "current_balance": 2641.1,
      "last_updated": "20260606"
    },
    "1119": {
      "current_balance": 935.54,
      "last_updated": "20260606"
    },
    "308": {
      "current_balance": 595.2,
      "last_updated": "20260606"
    },
    "825": {
      "current_balance": 374.32,
      "last_updated": "20260606"
    },
    "823": {
      "current_balance": 927.4,
      "last_updated": "20260606"
    },
    "1004": {
      "current_balance": 1037.67,
      "last_updated": "20260606"
    },
    "117": {
      "current_balance": 1309.01,
      "last_updated": "20260606"
    },
    "0421": {
      "current_balance": 194.14,
      "last_updated": "20260606"
    },
    "524": {
      "current_balance": 1286.82,
      "last_updated": "20260606"
    },
    "802": {
      "current_balance": 1591.86,
      "last_updated": "20260606"
    },
    "118": {
      "current_balance": 445.3,
      "last_updated": "20260606"
    },
    "703": {
      "current_balance": 1573.0,
      "last_updated": "20260606"
    },
    "1015": {
      "current_balance": 1894.68,
      "last_updated": "20260606"
    },
    "708": {
      "current_balance": 264.35,
      "last_updated": "20260606"
    },
    "705": {
      "current_balance": 1452.47,
      "last_updated": "20260606"
    },
    "0205": {
      "current_balance": 1487.48,
      "last_updated": "20260606"
    },
    "404": {
      "current_balance": 586.42,
      "last_updated": "20260606"
    },
    "620": {
      "current_balance": 1909.66,
      "last_updated": "20260606"
    },
    "0715": {
      "current_balance": 869.95,
      "last_updated": "20260606"
    },
    "803": {
      "current_balance": 997.33,
      "last_updated": "20260606"
    },
    "410": {
      "current_balance": 715.3,
      "last_updated": "20260606"
    },
    "0309": {
      "current_balance": 1967.71,
      "last_updated": "20260606"
    },
    "715": {
      "current_balance": 869.95,
      "last_updated": "20260606"
    },
    "811": {
      "current_balance": 913.81,
      "last_updated": "20260606"
    },
    "1018": {
      "current_balance": 1999.82,
      "last_updated": "20260606"
    },
    "604": {
      "current_balance": 1109.82,
      "last_updated": "20260606"
    },
    "0705": {
      "current_balance": 1452.47,
      "last_updated": "20260606"
    },
    "806": {
      "current_balance": 985.26,
      "last_updated": "20260606"
    },
    "1111": {
      "current_balance": 532.62,
      "last_updated": "20260606"
    },
    "1206": {
      "current_balance": 1488.44,
      "last_updated": "20260606"
    },
    "723": {
      "current_balance": 742.73,
      "last_updated": "20260606"
    },
    "822": {
      "current_balance": 1858.08,
      "last_updated": "20260606"
    },
    "218": {
      "current_balance": 1.38,
      "last_updated": "20260606"
    },
    "1114": {
      "current_balance": 915.23,
      "last_updated": "20260606"
    },
    "906": {
      "current_balance": 898.64,
      "last_updated": "20260606"
    },
    "821": {
      "current_balance": 1047.92,
      "last_updated": "20260606"
    },
    "605": {
      "current_balance": 1829.23,
      "last_updated": "20260606"
    },
    "403": {
      "current_balance": 681.25,
      "last_updated": "20260606"
    },
    "712": {
      "current_balance": 2064.83,
      "last_updated": "20260606"
    },
    "421": {
      "current_balance": 194.14,
      "last_updated": "20260606"
    },
    "305": {
      "current_balance": 712.18,
      "last_updated": "20260606"
    },
    "1202": {
      "current_balance": 1000.54,
      "last_updated": "20260606"
    },
    "0811": {
      "current_balance": 913.81,
      "last_updated": "20260606"
    },
    "0220": {
      "current_balance": 1049.93,
      "last_updated": "20260606"
    },
    "1104": {
      "current_balance": 1197.72,
      "last_updated": "20260606"
    },
    "0102": {
      "current_balance": 1012.44,
      "last_updated": "20260606"
    },
    "104": {
      "current_balance": 1133.0,
      "last_updated": "20260606"
    },
    "217": {
      "current_balance": 104.35,
      "last_updated": "20260606"
    },
    "318": {
      "current_balance": 1625.26,
      "last_updated": "20260606"
    },
    "1118": {
      "current_balance": 989.85,
      "last_updated": "20260606"
    },
    "502": {
      "current_balance": 895.65,
      "last_updated": "20260606"
    },
    "602": {
      "current_balance": 988.27,
      "last_updated": "20260606"
    },
    "1023": {
      "current_balance": 1673.39,
      "last_updated": "20260606"
    },
    "111": {
      "current_balance": 45.14,
      "last_updated": "20260606"
    },
    "312": {
      "current_balance": 625.63,
      "last_updated": "20260605"
    },
    "907": {
      "current_balance": 2166.47,
      "last_updated": "20260606"
    },
    "607": {
      "current_balance": 2238.6,
      "last_updated": "20260606"
    },
    "824": {
      "current_balance": 1524.94,
      "last_updated": "20260606"
    },
    "0213": {
      "current_balance": 945.98,
      "last_updated": "20260606"
    },
    "615": {
      "current_balance": 1063.89,
      "last_updated": "20260606"
    },
    "1017": {
      "current_balance": 1812.78,
      "last_updated": "20260606"
    },
    "0207": {
      "current_balance": 1393.29,
      "last_updated": "20260606"
    },
    "1120": {
      "current_balance": 1596.73,
      "last_updated": "20260606"
    },
    "0407": {
      "current_balance": 980.57,
      "last_updated": "20260606"
    },
    "921": {
      "current_balance": 663.2,
      "last_updated": "20260606"
    },
    "815": {
      "current_balance": 2247.31,
      "last_updated": "20260606"
    },
    "324": {
      "current_balance": 83.29,
      "last_updated": "20260606"
    },
    "625": {
      "current_balance": 1143.85,
      "last_updated": "20260606"
    },
    "0110": {
      "current_balance": 1224.4,
      "last_updated": "20260606"
    },
    "717": {
      "current_balance": 1621.33,
      "last_updated": "20260606"
    },
    "902": {
      "current_balance": 511.52,
      "last_updated": "20260606"
    },
    "303": {
      "current_balance": 1716.6,
      "last_updated": "20260606"
    },
    "205": {
      "current_balance": 1487.48,
      "last_updated": "20260606"
    },
    "108": {
      "current_balance": 1612.31,
      "last_updated": "20260606"
    },
    "609": {
      "current_balance": 750.83,
      "last_updated": "20260606"
    },
    "320": {
      "current_balance": 776.89,
      "last_updated": "20260606"
    },
    "612": {
      "current_balance": 669.33,
      "last_updated": "20260606"
    },
    "521": {
      "current_balance": 867.16,
      "last_updated": "20260606"
    },
    "417": {
      "current_balance": 877.09,
      "last_updated": "20260606"
    },
    "1003": {
      "current_balance": 889.96,
      "last_updated": "20260606"
    },
    "120": {
      "current_balance": 583.78,
      "last_updated": "20260606"
    },
    "516": {
      "current_balance": 3101.5,
      "last_updated": "20260606"
    },
    "419": {
      "current_balance": 1590.34,
      "last_updated": "20260606"
    },
    "206": {
      "current_balance": 1842.37,
      "last_updated": "20260606"
    },
    "903": {
      "current_balance": 1378.78,
      "last_updated": "20260606"
    },
    "919": {
      "current_balance": 1096.44,
      "last_updated": "20260606"
    },
    "310": {
      "current_balance": 2375.39,
      "last_updated": "20260606"
    },
    "917": {
      "current_balance": 1070.66,
      "last_updated": "20260606"
    },
    "317": {
      "current_balance": 2061.65,
      "last_updated": "20260606"
    },
    "0701": {
      "current_balance": 1319.0,
      "last_updated": "20260606"
    },
    "0825": {
      "current_balance": 374.32,
      "last_updated": "20260606"
    },
    "105": {
      "current_balance": 947.93,
      "last_updated": "20260606"
    },
    "910": {
      "current_balance": 1984.44,
      "last_updated": "20260606"
    },
    "812": {
      "current_balance": 593.4,
      "last_updated": "20260606"
    },
    "422": {
      "current_balance": 763.03,
      "last_updated": "20260606"
    },
    "0920": {
      "current_balance": 1335.49,
      "last_updated": "20260606"
    },
    "414": {
      "current_balance": 754.03,
      "last_updated": "20260606"
    },
    "725": {
      "current_balance": 983.88,
      "last_updated": "20260606"
    },
    "314": {
      "current_balance": 748.42,
      "last_updated": "20260606"
    },
    "112": {
      "current_balance": 902.66,
      "last_updated": "20260606"
    },
    "306": {
      "current_balance": 26.35,
      "last_updated": "20260606"
    },
    "0703": {
      "current_balance": 1573.0,
      "last_updated": "20260606"
    },
    "1020": {
      "current_balance": 1023.85,
      "last_updated": "20260606"
    },
    "0706": {
      "current_balance": 537.68,
      "last_updated": "20260606"
    },
    "114": {
      "current_balance": 390.15,
      "last_updated": "20260606"
    },
    "911": {
      "current_balance": 2515.94,
      "last_updated": "20260606"
    },
    "424": {
      "current_balance": 344.61,
      "last_updated": "20260606"
    },
    "0404": {
      "current_balance": 586.42,
      "last_updated": "20260606"
    },
    "1005": {
      "current_balance": 810.81,
      "last_updated": "20260606"
    },
    "720": {
      "current_balance": 1664.28,
      "last_updated": "20260606"
    },
    "222": {
      "current_balance": 750.76,
      "last_updated": "20260606"
    },
    "0901": {
      "current_balance": 996.14,
      "last_updated": "20260606"
    },
    "1221": {
      "current_balance": 213.59,
      "last_updated": "20260606"
    },
    "901": {
      "current_balance": 996.14,
      "last_updated": "20260606"
    },
    "1116": {
      "current_balance": 39.39,
      "last_updated": "20260606"
    },
    "1007": {
      "current_balance": 836.72,
      "last_updated": "20260606"
    },
    "1113": {
      "current_balance": 764.43,
      "last_updated": "20260606"
    },
    "1006": {
      "current_balance": 1208.27,
      "last_updated": "20260606"
    },
    "313": {
      "current_balance": 860.97,
      "last_updated": "20260606"
    },
    "925": {
      "current_balance": 608.51,
      "last_updated": "20260606"
    },
    "608": {
      "current_balance": 2233.28,
      "last_updated": "20260606"
    },
    "1109": {
      "current_balance": 89.35,
      "last_updated": "20260606"
    },
    "621": {
      "current_balance": 2037.33,
      "last_updated": "20260606"
    },
    "503": {
      "current_balance": 1037.7,
      "last_updated": "20260606"
    },
    "915": {
      "current_balance": 2175.67,
      "last_updated": "20260606"
    },
    "1209": {
      "current_balance": 938.2,
      "last_updated": "20260606"
    },
    "623": {
      "current_balance": 1750.18,
      "last_updated": "20260606"
    },
    "0507": {
      "current_balance": 678.4,
      "last_updated": "20260606"
    },
    "0115": {
      "current_balance": 152.05,
      "last_updated": "20260606"
    },
    "0806": {
      "current_balance": 985.26,
      "last_updated": "20260606"
    },
    "1121": {
      "current_balance": 1777.3,
      "last_updated": "20260606"
    },
    "704": {
      "current_balance": 1298.94,
      "last_updated": "20260606"
    },
    "325": {
      "current_balance": 934.89,
      "last_updated": "20260606"
    },
    "522": {
      "current_balance": 935.43,
      "last_updated": "20260606"
    },
    "505": {
      "current_balance": 1666.88,
      "last_updated": "20260606"
    },
    "1009": {
      "current_balance": 2335.14,
      "last_updated": "20260606"
    },
    "716": {
      "current_balance": 1538.93,
      "last_updated": "20260606"
    },
    "1214": {
      "current_balance": 988.14,
      "last_updated": "20260606"
    },
    "1117": {
      "current_balance": 960.42,
      "last_updated": "20260606"
    },
    "0318": {
      "current_balance": 1625.26,
      "last_updated": "20260606"
    },
    "1014": {
      "current_balance": 816.84,
      "last_updated": "20260606"
    },
    "0313": {
      "current_balance": 860.97,
      "last_updated": "20260606"
    },
    "519": {
      "current_balance": 1569.3,
      "last_updated": "20260606"
    },
    "1124": {
      "current_balance": 1572.62,
      "last_updated": "20260606"
    },
    "115": {
      "current_balance": 152.05,
      "last_updated": "20260606"
    },
    "0820": {
      "current_balance": 847.76,
      "last_updated": "20260606"
    },
    "501": {
      "current_balance": 1327.03,
      "last_updated": "20260606"
    },
    "0903": {
      "current_balance": 1378.78,
      "last_updated": "20260606"
    },
    "02舍第2层222房间": {
      "current_balance": 750.76,
      "last_updated": "20260606"
    },
    "202": {
      "current_balance": 939.59,
      "last_updated": "20260606"
    },
    "709": {
      "current_balance": 797.08,
      "last_updated": "20260606"
    },
    "1210": {
      "current_balance": 1750.76,
      "last_updated": "20260606"
    },
    "401": {
      "current_balance": 1191.32,
      "last_updated": "20260606"
    },
    "819": {
      "current_balance": 2213.73,
      "last_updated": "20260606"
    },
    "610": {
      "current_balance": 959.37,
      "last_updated": "20260606"
    },
    "1205": {
      "current_balance": 1458.51,
      "last_updated": "20260606"
    },
    "714": {
      "current_balance": 2030.34,
      "last_updated": "20260606"
    },
    "0910": {
      "current_balance": 1984.44,
      "last_updated": "20260606"
    },
    "1002": {
      "current_balance": 1015.35,
      "last_updated": "20260606"
    },
    "412": {
      "current_balance": 880.03,
      "last_updated": "20260606"
    },
    "1105": {
      "current_balance": 1985.79,
      "last_updated": "20260606"
    },
    "304": {
      "current_balance": 1130.74,
      "last_updated": "20260606"
    },
    "1207": {
      "current_balance": 1343.6,
      "last_updated": "20260606"
    },
    "116": {
      "current_balance": 665.6,
      "last_updated": "20260606"
    },
    "1008": {
      "current_balance": 921.32,
      "last_updated": "20260606"
    },
    "1102": {
      "current_balance": 1431.26,
      "last_updated": "20260606"
    },
    "801": {
      "current_balance": 1151.76,
      "last_updated": "20260606"
    },
    "1222": {
      "current_balance": 163.64,
      "last_updated": "20260606"
    },
    "405": {
      "current_balance": 803.44,
      "last_updated": "20260606"
    },
    "1103": {
      "current_balance": 1720.78,
      "last_updated": "20260606"
    },
    "425": {
      "current_balance": 849.02,
      "last_updated": "20260606"
    },
    "816": {
      "current_balance": 1692.4,
      "last_updated": "20260606"
    },
    "810": {
      "current_balance": 1335.95,
      "last_updated": "20260606"
    },
    "201": {
      "current_balance": 663.09,
      "last_updated": "20260606"
    },
    "0623": {
      "current_balance": 1750.18,
      "last_updated": "20260606"
    },
    "807": {
      "current_balance": 978.23,
      "last_updated": "20260606"
    },
    "0907": {
      "current_balance": 2166.47,
      "last_updated": "20260606"
    },
    "316": {
      "current_balance": 857.25,
      "last_updated": "20260606"
    },
    "0209": {
      "current_balance": 1071.04,
      "last_updated": "20260606"
    },
    "407": {
      "current_balance": 980.57,
      "last_updated": "20260606"
    },
    "418": {
      "current_balance": 1095.11,
      "last_updated": "20260606"
    },
    "423": {
      "current_balance": 748.99,
      "last_updated": "20260606"
    },
    "509": {
      "current_balance": 816.9,
      "last_updated": "20260606"
    },
    "225": {
      "current_balance": 665.19,
      "last_updated": "20260606"
    },
    "805": {
      "current_balance": 1749.12,
      "last_updated": "20260606"
    },
    "922": {
      "current_balance": 536.96,
      "last_updated": "20260606"
    },
    "406": {
      "current_balance": 1735.83,
      "last_updated": "20260606"
    },
    "409": {
      "current_balance": 1014.09,
      "last_updated": "20260606"
    },
    "1224": {
      "current_balance": 0.0,
      "last_updated": "20260606"
    },
    "1215": {
      "current_balance": 654.22,
      "last_updated": "20260606"
    },
    "706": {
      "current_balance": 537.68,
      "last_updated": "20260606"
    },
    "517": {
      "current_balance": 338.23,
      "last_updated": "20260606"
    },
    "1110": {
      "current_balance": 581.56,
      "last_updated": "20260606"
    },
    "814": {
      "current_balance": 1094.44,
      "last_updated": "20260606"
    },
    "216": {
      "current_balance": 865.77,
      "last_updated": "20260606"
    },
    "1107": {
      "current_balance": 1619.3,
      "last_updated": "20260606"
    },
    "507": {
      "current_balance": 678.4,
      "last_updated": "20260606"
    },
    "1123": {
      "current_balance": 1330.57,
      "last_updated": "20260606"
    },
    "924": {
      "current_balance": 1270.16,
      "last_updated": "20260606"
    },
    "818": {
      "current_balance": 1821.39,
      "last_updated": "20260606"
    },
    "119": {
      "current_balance": 39.99,
      "last_updated": "20260606"
    },
    "1217": {
      "current_balance": 552.27,
      "last_updated": "20260606"
    },
    "616": {
      "current_balance": 1001.19,
      "last_updated": "20260606"
    },
    "904": {
      "current_balance": 2013.28,
      "last_updated": "20260606"
    },
    "1125": {
      "current_balance": 1310.91,
      "last_updated": "20260606"
    },
    "701": {
      "current_balance": 1319.0,
      "last_updated": "20260606"
    },
    "109": {
      "current_balance": 663.46,
      "last_updated": "20260606"
    },
    "0504": {
      "current_balance": 1070.37,
      "last_updated": "20260606"
    },
    "212": {
      "current_balance": 2130.77,
      "last_updated": "20260606"
    },
    "208": {
      "current_balance": 988.2,
      "last_updated": "20260606"
    },
    "411": {
      "current_balance": 2400.85,
      "last_updated": "20260606"
    },
    "319": {
      "current_balance": 1040.28,
      "last_updated": "20260606"
    },
    "611": {
      "current_balance": 804.28,
      "last_updated": "20260606"
    },
    "508": {
      "current_balance": 947.11,
      "last_updated": "20260606"
    },
    "512": {
      "current_balance": 960.61,
      "last_updated": "20260606"
    },
    "420": {
      "current_balance": 693.6,
      "last_updated": "20260606"
    },
    "210": {
      "current_balance": 2121.4,
      "last_updated": "20260606"
    },
    "617": {
      "current_balance": 1774.64,
      "last_updated": "20260606"
    },
    "913": {
      "current_balance": 606.54,
      "last_updated": "20260606"
    },
    "515": {
      "current_balance": 1516.55,
      "last_updated": "20260606"
    },
    "908": {
      "current_balance": 2006.95,
      "last_updated": "20260606"
    },
    "1216": {
      "current_balance": 1806.78,
      "last_updated": "20260606"
    },
    "722": {
      "current_balance": 1143.35,
      "last_updated": "20260606"
    },
    "914": {
      "current_balance": 2161.99,
      "last_updated": "20260606"
    },
    "1012": {
      "current_balance": 995.49,
      "last_updated": "20260606"
    },
    "820": {
      "current_balance": 847.76,
      "last_updated": "20260606"
    },
    "1213": {
      "current_balance": 1478.44,
      "last_updated": "20260606"
    },
    "1223": {
      "current_balance": 11.94,
      "last_updated": "20260606"
    },
    "1220": {
      "current_balance": 498.63,
      "last_updated": "20260606"
    },
    "211": {
      "current_balance": 813.9,
      "last_updated": "20260606"
    },
    "918": {
      "current_balance": 879.68,
      "last_updated": "20260606"
    },
    "209": {
      "current_balance": 1071.04,
      "last_updated": "20260606"
    },
    "511": {
      "current_balance": 2927.69,
      "last_updated": "20260606"
    },
    "613": {
      "current_balance": 1084.43,
      "last_updated": "20260606"
    },
    "1203": {
      "current_balance": 837.03,
      "last_updated": "20260606"
    },
    "523": {
      "current_balance": 1442.2,
      "last_updated": "20260606"
    },
    "1112": {
      "current_balance": 2292.84,
      "last_updated": "20260606"
    },
    "203": {
      "current_balance": 893.32,
      "last_updated": "20260606"
    },
    "1225": {
      "current_balance": 130.65,
      "last_updated": "20260606"
    },
    "0217": {
      "current_balance": 104.35,
      "last_updated": "20260606"
    },
    "916": {
      "current_balance": 1635.24,
      "last_updated": "20260606"
    },
    "804": {
      "current_balance": 2376.78,
      "last_updated": "20260606"
    },
    "718": {
      "current_balance": 1547.58,
      "last_updated": "20260606"
    },
    "0921": {
      "current_balance": 663.2,
      "last_updated": "20260606"
    },
    "323": {
      "current_balance": 1059.35,
      "last_updated": "20260606"
    },
    "1025": {
      "current_balance": 1149.96,
      "last_updated": "20260606"
    },
    "1211": {
      "current_balance": 935.7,
      "last_updated": "20260606"
    },
    "506": {
      "current_balance": 1958.86,
      "last_updated": "20260606"
    },
    "1011": {
      "current_balance": 627.27,
      "last_updated": "20260606"
    },
    "302": {
      "current_balance": 845.13,
      "last_updated": "20260606"
    },
    "1101": {
      "current_balance": 2224.29,
      "last_updated": "20260606"
    },
    "1022": {
      "current_balance": 984.33,
      "last_updated": "20260606"
    },
    "219": {
      "current_balance": 1594.76,
      "last_updated": "20260606"
    },
    "912": {
      "current_balance": 2385.0,
      "last_updated": "20260606"
    },
    "514": {
      "current_balance": 1033.1,
      "last_updated": "20260606"
    },
    "220": {
      "current_balance": 1049.93,
      "last_updated": "20260606"
    },
    "223": {
      "current_balance": 1443.87,
      "last_updated": "20260606"
    },
    "721": {
      "current_balance": 439.27,
      "last_updated": "20260606"
    },
    "1010": {
      "current_balance": 1056.22,
      "last_updated": "20260606"
    },
    "923": {
      "current_balance": 791.24,
      "last_updated": "20260606"
    },
    "1013": {
      "current_balance": 562.4,
      "last_updated": "20260606"
    },
    "618": {
      "current_balance": 1249.59,
      "last_updated": "20260606"
    },
    "0805": {
      "current_balance": 1749.12,
      "last_updated": "20260606"
    },
    "0311": {
      "current_balance": 1010.37,
      "last_updated": "20260606"
    },
    "920": {
      "current_balance": 1335.49,
      "last_updated": "20260606"
    },
    "322": {
      "current_balance": 1512.89,
      "last_updated": "20260606"
    },
    "402": {
      "current_balance": 1439.9,
      "last_updated": "20260606"
    },
    "416": {
      "current_balance": 1281.41,
      "last_updated": "20260606"
    },
    "510": {
      "current_balance": 797.51,
      "last_updated": "20260606"
    },
    "525": {
      "current_balance": 1057.21,
      "last_updated": "20260606"
    },
    "307": {
      "current_balance": 580.47,
      "last_updated": "20260606"
    },
    "711": {
      "current_balance": 1542.91,
      "last_updated": "20260606"
    },
    "1021": {
      "current_balance": 2390.74,
      "last_updated": "20260606"
    },
    "622": {
      "current_balance": 707.94,
      "last_updated": "20260606"
    },
    "1115": {
      "current_balance": 1062.41,
      "last_updated": "20260606"
    },
    "1218": {
      "current_balance": 1715.68,
      "last_updated": "20260606"
    },
    "0120": {
      "current_balance": 583.78,
      "last_updated": "20260606"
    },
    "614": {
      "current_balance": 1462.5,
      "last_updated": "20260606"
    },
    "813": {
      "current_balance": 2237.04,
      "last_updated": "20260606"
    },
    "624": {
      "current_balance": 1180.13,
      "last_updated": "20260606"
    },
    "110": {
      "current_balance": 1224.4,
      "last_updated": "20260606"
    },
    "713": {
      "current_balance": 897.94,
      "last_updated": "20260606"
    },
    "207": {
      "current_balance": 1393.29,
      "last_updated": "20260606"
    },
    "603": {
      "current_balance": 1327.86,
      "last_updated": "20260606"
    },
    "311": {
      "current_balance": 1010.37,
      "last_updated": "20260606"
    },
    "315": {
      "current_balance": 917.66,
      "last_updated": "20260606"
    },
    "1204": {
      "current_balance": 1122.87,
      "last_updated": "20260606"
    },
    "0408": {
      "current_balance": 2641.1,
      "last_updated": "20260606"
    },
    "1001": {
      "current_balance": 1120.84,
      "last_updated": "20260606"
    },
    "301": {
      "current_balance": 1822.14,
      "last_updated": "20260606"
    },
    "214": {
      "current_balance": 1761.81,
      "last_updated": "20260606"
    },
    "0521": {
      "current_balance": 867.16,
      "last_updated": "20260606"
    },
    "213": {
      "current_balance": 945.98,
      "last_updated": "20260606"
    }
  }
}